mala/__init__.py
mala/version.py
mala/common/__init__.py
mala/common/check_modules.py
mala/common/json_serializable.py
mala/common/parallelizer.py
mala/common/parameters.py
mala/common/physical_data.py
mala/datageneration/__init__.py
mala/datageneration/ofdft_initializer.py
mala/datageneration/trajectory_analyzer.py
mala/datahandling/__init__.py
mala/datahandling/data_converter.py
mala/datahandling/data_handler.py
mala/datahandling/data_handler_base.py
mala/datahandling/data_repo.py
mala/datahandling/data_scaler.py
mala/datahandling/data_shuffler.py
mala/datahandling/fast_tensor_dataset.py
mala/datahandling/lazy_load_dataset.py
mala/datahandling/lazy_load_dataset_single.py
mala/datahandling/ldos_aligner.py
mala/datahandling/multi_lazy_load_data_loader.py
mala/datahandling/snapshot.py
mala/descriptors/__init__.py
mala/descriptors/ace.py
mala/descriptors/atomic_density.py
mala/descriptors/bispectrum.py
mala/descriptors/descriptor.py
mala/descriptors/lammps_utils.py
mala/descriptors/minterpy_descriptors.py
mala/descriptors/acelib/__init__.py
mala/descriptors/acelib/ace_potential.py
mala/descriptors/acelib/clebsch_gordan_coupling.py
mala/descriptors/acelib/common_utils.py
mala/descriptors/acelib/coupling_utils.py
mala/descriptors/acelib/symmetric_group_manipulations.py
mala/descriptors/acelib/tree_sorting.py
mala/descriptors/acelib/wigner_coupling.py
mala/descriptors/acelib/young.py
mala/interfaces/__init__.py
mala/interfaces/ase_calculator.py
mala/network/__init__.py
mala/network/acsd_analyzer.py
mala/network/descriptor_scoring_optimizer.py
mala/network/hyper_opt.py
mala/network/hyper_opt_naswot.py
mala/network/hyper_opt_oat.py
mala/network/hyper_opt_optuna.py
mala/network/hyperparameter.py
mala/network/hyperparameter_descriptor_scoring.py
mala/network/hyperparameter_naswot.py
mala/network/hyperparameter_oat.py
mala/network/hyperparameter_optuna.py
mala/network/multi_training_pruner.py
mala/network/mutual_information_analyzer.py
mala/network/naswot_pruner.py
materials_learning_algorithms-1.4.0.dist-info/LICENSE
materials_learning_algorithms-1.4.0.dist-info/METADATA
materials_learning_algorithms-1.4.0.dist-info/WHEEL
materials_learning_algorithms-1.4.0.dist-info/top_level.txt
materials_learning_algorithms-1.4.0.dist-info/RECORD
