Metadata-Version: 2.1
Name: materials-learning-algorithms
Version: 1.4.0
Summary: Materials Learning Algorithms. A framework for machine learning materials properties from first-principles data.
Home-page: https://github.com/mala-project/mala
Author: MALA developers
License: BSD 3-Clause License
Requires-Python: >=3.10.4
License-File: LICENSE
Requires-Dist: torch
Requires-Dist: numpy >=2
Requires-Dist: ase
Requires-Dist: mpmath
Requires-Dist: optuna
Requires-Dist: scipy
Requires-Dist: pandas
Requires-Dist: tensorboard
Requires-Dist: openpmd-api
Requires-Dist: scikit-spatial
Requires-Dist: tqdm
Requires-Dist: mendeleev >=1.0.0
Requires-Dist: sympy
Requires-Dist: meson
Requires-Dist: ninja
Provides-Extra: dev
Requires-Dist: bump2version ; extra == 'dev'
Provides-Extra: doc
Requires-Dist: docutils ==0.20.1 ; extra == 'doc'
Requires-Dist: Sphinx ==7.3.7 ; extra == 'doc'
Requires-Dist: sphinx-rtd-theme ==2.0.0 ; extra == 'doc'
Requires-Dist: myst-parser ==3.0.1 ; extra == 'doc'
Requires-Dist: sphinx-markdown-tables ==0.0.17 ; extra == 'doc'
Requires-Dist: sphinx-copybutton ==0.5.2 ; extra == 'doc'
Provides-Extra: experimental
Requires-Dist: asap3 ; extra == 'experimental'
Requires-Dist: dftpy ; extra == 'experimental'
Requires-Dist: minterpy ; extra == 'experimental'
Provides-Extra: mpi
Requires-Dist: mpi4py ; extra == 'mpi'
Provides-Extra: opt
Requires-Dist: oapackage ; extra == 'opt'
Requires-Dist: scikit-learn ; extra == 'opt'
Provides-Extra: test
Requires-Dist: pytest ; extra == 'test'
Requires-Dist: pytest-cov ; extra == 'test'
